Metadata-Version: 2.1
Name: py-newscollector
Version: 1.0.0
Summary: NewsCollector - Python script for automated collection of most relevant news articles of the day.
Home-page: https://github.com/elisemercury/NewsCollector
Author: Elise Landman
Author-email: elisejlandman@hotmail.com
License: MIT
Download-URL: https://github.com/elisemercury/NewsCollector/archive/refs/tags/v1.0.0.tar.gz
Keywords: news,collection,automation,newsletter
Platform: UNKNOWN
Classifier: Development Status :: 5 - Production/Stable
Classifier: Intended Audience :: Developers
Classifier: Topic :: Software Development :: Build Tools
Classifier: License :: OSI Approved :: MIT License
Classifier: Programming Language :: Python :: 3.7
Classifier: Programming Language :: Python :: 3.8
Classifier: Programming Language :: Python :: 3.9
